pulsestreamer/__init__.py
pulsestreamer/__main__.py
pulsestreamer/enums.py
pulsestreamer/findPulseStreamers.py
pulsestreamer/sequence.py
pulsestreamer/version.py
pulsestreamer/grpc/__init__.py
pulsestreamer/grpc/pulse_streamer_grpc.py
pulsestreamer/grpc/pulse_streamer_pb2.py
pulsestreamer/grpc/pulse_streamer_pb2_grpc.py
pulsestreamer/jrpc/__init__.py
pulsestreamer/jrpc/pulse_streamer_jrpc.py
pulsestreamer-1.6.2.dist-info/LICENSE.txt
pulsestreamer-1.6.2.dist-info/WHEEL
pulsestreamer-1.6.2.dist-info/METADATA
pulsestreamer-1.6.2.dist-info/RECORD
